lychrel-0.8.0.dist-info/METADATA
lychrel-0.8.0.dist-info/WHEEL
lychrel-0.8.0.dist-info/licenses/LICENSE
lychrel/__init__.py
lychrel/lychrel.abi3.so
lychrel/py.py
lychrel-0.8.0.dist-info/RECORD
