Metadata-Version: 2.4
Name: lychrel
Version: 0.8.0
Classifier: Intended Audience :: Education
Classifier: Intended Audience :: Science/Research
Classifier: Programming Language :: Python :: 3
Classifier: Programming Language :: Python :: Implementation :: CPython
Classifier: Programming Language :: Rust
Classifier: Topic :: Scientific/Engineering :: Mathematics
License-File: LICENSE
Summary: A collection of functions to play with Lychrel numbers and other funny mathematical problems
Home-Page: https://github.com/alesanfra/lychrel
Author-email: Alessio Sanfratello <sanfra90@gmail.com>
Requires-Python: >=3.7
Project-URL: Homepage, https://github.com/alesanfra/lychrel
Project-URL: Source, https://github.com/alesanfra/lychrel
